{
  "nodes": [
    {
      "id": "api-function",
      "type": "default",
      "data": { "label": "API Function" },
      "position": { "x": 50, "y": 50 },
      "style": { "background": "#9333ea", "color": "white", "border": "2px solid #7e22ce", "borderRadius": "8px", "width": "150px", "fontWeight": "bold" },
      "handles": [
        { "type": "source", "position": "right", "id": "api-seq1" }
      ]
    },
    {
      "id": "get-request",
      "type": "default",
      "data": { "label": "GET Request" },
      "position": { "x": 300, "y": 50 },
      "style": { "background": "#06b6d4", "color": "white", "border": "2px solid #0891b2", "borderRadius": "8px", "width": "140px" },
      "handles": [
        { "type": "target", "position": "left", "id": "get-request-target" },
        { "type": "source", "position": "right", "id": "get-request-out" }
      ]
    },
    {
      "id": "parse-params",
      "type": "default",
      "data": { "label": "Parse Params" },
      "position": { "x": 480, "y": 50 },
      "style": { "background": "#06b6d4", "color": "white", "border": "2px solid #0891b2", "borderRadius": "8px", "width": "140px" },
      "handles": [
        { "type": "target", "position": "left", "id": "parse-params-target" },
        { "type": "source", "position": "right", "id": "parse-params-out" }
      ]
    },
    {
      "id": "fetch-users",
      "type": "default",
      "data": { "label": "Fetch Users" },
      "position": { "x": 650, "y": 50 },
      "style": { "background": "#06b6d4", "color": "white", "border": "2px solid #0891b2", "borderRadius": "8px", "width": "140px" },
      "handles": [
        { "type": "target", "position": "left", "id": "fetch-users-target" },
        { "type": "source", "position": "right", "id": "fetch-users-out" }
      ]
    },
    {
      "id": "find-user",
      "type": "default",
      "data": { "label": "Find User" },
      "position": { "x": 820, "y": 50 },
      "style": { "background": "#06b6d4", "color": "white", "border": "2px solid #0891b2", "borderRadius": "8px", "width": "140px" },
      "handles": [
        { "type": "target", "position": "left", "id": "find-user-target" },
        { "type": "source", "position": "right", "id": "find-user-found" },
        { "type": "source", "position": "right", "id": "find-user-not-found" }
      ]
    },
    {
      "id": "return-user",
      "type": "default",
      "data": { "label": "Return User" },
      "position": { "x": 990, "y": 20 },
      "style": { "background": "#22c55e", "color": "black", "border": "2px solid #16a34a", "borderRadius": "8px", "width": "140px" },
      "handles": [{ "type": "target", "position": "left", "id": "return-user-target" }]
    },
    {
      "id": "return-error",
      "type": "default",
      "data": { "label": "Return Error" },
      "position": { "x": 990, "y": 80 },
      "style": { "background": "#ef4444", "color": "white", "border": "2px solid #dc2626", "borderRadius": "8px", "width": "140px" },
      "handles": [{ "type": "target", "position": "left", "id": "return-error-target" }]
    }
  ],
  "edges": [
    {
      "id": "api-to-get-request",
      "source": "api-function",
      "target": "get-request",
      "sourceHandle": "api-seq1",
      "targetHandle": "get-request-target"
    },
    {
      "id": "get-to-parse",
      "source": "get-request",
      "target": "parse-params",
      "sourceHandle": "get-request-out",
      "targetHandle": "parse-params-target"
    },
    {
      "id": "parse-to-fetch",
      "source": "parse-params",
      "target": "fetch-users",
      "sourceHandle": "parse-params-out",
      "targetHandle": "fetch-users-target"
    },
    {
      "id": "fetch-to-find",
      "source": "fetch-users",
      "target": "find-user",
      "sourceHandle": "fetch-users-out",
      "targetHandle": "find-user-target"
    },
    {
      "id": "find-user-found-path",
      "source": "find-user",
      "target": "return-user",
      "sourceHandle": "find-user-found",
      "targetHandle": "return-user-target"
    },
    {
      "id": "find-user-not-found-path",
      "source": "find-user",
      "target": "return-error",
      "sourceHandle": "find-user-not-found",
      "targetHandle": "return-error-target"
    }
  ]
}
